poker_gym/__init__.py
poker_gym/envs/__init__.py
poker_gym/envs/poker_env.py
poker_gym-0.1.0.1.dist-info/WHEEL
poker_gym-0.1.0.1.dist-info/METADATA
poker_gym-0.1.0.1.dist-info/RECORD
